clar_cloc/__init__.py
clar_cloc/cli.py
clar_cloc/count.py
clar_cloc/counter.py
clar_cloc-0.1.1.dist-info/METADATA
clar_cloc-0.1.1.dist-info/WHEEL
clar_cloc-0.1.1.dist-info/entry_points.txt
clar_cloc-0.1.1.dist-info/top_level.txt
clar_cloc-0.1.1.dist-info/RECORD
