Metadata-Version: 2.1
Name: clar-cloc
Version: 0.1.1
Summary: A CLI tool to count lines in Clarity (.clar) files
Home-page: https://github.com/yourusername/clar_cloc
Author: Kristian Apostolov
Author-email: kristianapostolovcontacts@gmail.com
Classifier: Programming Language :: Python :: 3.12
Classifier: License :: OSI Approved :: MIT License
Classifier: Operating System :: OS Independent
Requires-Python: >=3.12
Requires-Dist: click
Requires-Dist: tabulate
Requires-Dist: setuptools
